mikrokondo_tools/__about__.py
mikrokondo_tools/__init__.py
mikrokondo_tools/__main__.py
mikrokondo_tools/cli/__init__.py
mikrokondo_tools/cli/download/__init__.py
mikrokondo_tools/cli/download/download.py
mikrokondo_tools/cli/format/__init__.py
mikrokondo_tools/cli/samplesheet/__init__.py
mikrokondo_tools/download/__init__.py
mikrokondo_tools/download/download.py
mikrokondo_tools/format/__init__.py
mikrokondo_tools/format/format.py
mikrokondo_tools/samplesheet/__init__.py
mikrokondo_tools/samplesheet/samplesheet.py
mikrokondo_tools/utils/__init__.py
mikrokondo_tools-0.0.1rc0.dist-info/METADATA
mikrokondo_tools-0.0.1rc0.dist-info/WHEEL
mikrokondo_tools-0.0.1rc0.dist-info/entry_points.txt
mikrokondo_tools-0.0.1rc0.dist-info/licenses/LICENSE.txt
mikrokondo_tools-0.0.1rc0.dist-info/RECORD
