Metadata-Version: 2.3
Name: mikrokondo-tools
Version: 0.0.1rc0
Project-URL: Documentation, https://github.com/unknown/mikrokondo-tools#readme
Project-URL: Issues, https://github.com/unknown/mikrokondo-tools/issues
Project-URL: Source, https://github.com/unknown/mikrokondo-tools
Author-email: Matthew Wells <mattheww9514@gmail.com>
License-Expression: MIT
License-File: LICENSE.txt
Classifier: Development Status :: 4 - Beta
Classifier: Programming Language :: Python
Classifier: Programming Language :: Python :: 3.8
Classifier: Programming Language :: Python :: 3.9
Classifier: Programming Language :: Python :: 3.10
Classifier: Programming Language :: Python :: 3.11
Classifier: Programming Language :: Python :: 3.12
Classifier: Programming Language :: Python :: Implementation :: CPython
Classifier: Programming Language :: Python :: Implementation :: PyPy
Requires-Python: >=3.8
Requires-Dist: click
Requires-Dist: jsonschema
Requires-Dist: requests
